aiovty/__init__.py
aiovty/client.py
aiovty-0.0.3.dist-info/LICENSE
aiovty-0.0.3.dist-info/METADATA
aiovty-0.0.3.dist-info/WHEEL
aiovty-0.0.3.dist-info/top_level.txt
aiovty-0.0.3.dist-info/RECORD
