Metadata-Version: 2.1
Name: aiovty
Version: 0.0.3
Summary: A python asyncio implementation for VTY protocol
Home-page: https://github.com/matan1008/aiovty
Author: Matan Perelman
Project-URL: aiovty, https://github.com/matan1008/aiovty
Classifier: Programming Language :: Python :: 3.8
Classifier: Programming Language :: Python :: 3.9
Classifier: Programming Language :: Python :: 3.10
License-File: LICENSE
